code_diff_review-2.0.1.dist-info/licenses/LICENSE
src/__init__.py
src/publishers.py
src/script.py
code_diff_review-2.0.1.dist-info/METADATA
code_diff_review-2.0.1.dist-info/WHEEL
code_diff_review-2.0.1.dist-info/entry_points.txt
code_diff_review-2.0.1.dist-info/top_level.txt
code_diff_review-2.0.1.dist-info/RECORD
